ro/synth_ro_top.v
/* Generated by Yosys 0.43+22 (git sha1 118b2829d, g++ 12.2.0-14 -fPIC -Os) */

(* src = "notModule.v:1.1-8.10" *)
module notGate(a, inversedA);
  (* src = "notModule.v:3.7-3.8" *)
  input a;
  wire a;
  (* src = "notModule.v:4.8-4.17" *)
  output inversedA;
  wire inversedA;
  assign inversedA = ~a;
endmodule

(* src = "randModule.v:1.1-13.10" *)
module randModule(en, randOut);
  (* src = "randModule.v:2.11-2.13" *)
  input en;
  wire en;
  (* src = "randModule.v:3.12-3.19" *)
  output randOut;
  wire randOut;
  (* src = "randModule.v:5.10-5.12" *)
  wire w0;
  (* src = "randModule.v:6.10-6.12" *)
  wire w1;
  (* src = "randModule.v:7.10-7.12" *)
  wire w2;
  assign w0 = ~(en & w2);
  (* module_not_derived = 32'd1 *)
  (* src = "randModule.v:10.13-10.30" *)
  notGate notGate_1 (
    .a(w0),
    .inversedA(w1)
  );
  (* module_not_derived = 32'd1 *)
  (* src = "randModule.v:11.13-11.30" *)
  notGate notGate_2 (
    .a(w1),
    .inversedA(w2)
  );
  assign randOut = w2;
endmodule

(* top =  1  *)
(* src = "ro_top.v:1.1-44.10" *)
module ro_top(clk, en, d_out);
  (* src = "ro_top.v:2.11-2.14" *)
  input clk;
  wire clk;
  (* src = "ro_top.v:3.17-3.22" *)
  output [7:0] d_out;
  wire [7:0] d_out;
  (* src = "ro_top.v:5.14-5.28" *)
  reg [7:0] d_out_internal;
  (* src = "ro_top.v:2.16-2.18" *)
  input en;
  wire en;
  (* src = "ro_top.v:6.16-6.22" *)
  wire [15:0] ro_out;
  (* src = "ro_top.v:7.15-7.22" *)
  wire [7:0] xor_out;
  assign xor_out[0] = ro_out[1] ^ ro_out[0];
  assign xor_out[1] = ro_out[3] ^ ro_out[2];
  assign xor_out[2] = ro_out[5] ^ ro_out[4];
  assign xor_out[3] = ro_out[7] ^ ro_out[6];
  assign xor_out[4] = ro_out[9] ^ ro_out[8];
  assign xor_out[5] = ro_out[11] ^ ro_out[10];
  assign xor_out[6] = ro_out[13] ^ ro_out[12];
  assign xor_out[7] = ro_out[15] ^ ro_out[14];
  (* src = "ro_top.v:38.5-40.8" *)
  always @(posedge clk)
    d_out_internal[1] <= xor_out[1];
  (* src = "ro_top.v:38.5-40.8" *)
  always @(posedge clk)
    d_out_internal[2] <= xor_out[2];
  (* src = "ro_top.v:38.5-40.8" *)
  always @(posedge clk)
    d_out_internal[3] <= xor_out[3];
  (* src = "ro_top.v:38.5-40.8" *)
  always @(posedge clk)
    d_out_internal[4] <= xor_out[4];
  (* src = "ro_top.v:38.5-40.8" *)
  always @(posedge clk)
    d_out_internal[5] <= xor_out[5];
  (* src = "ro_top.v:38.5-40.8" *)
  always @(posedge clk)
    d_out_internal[6] <= xor_out[6];
  (* src = "ro_top.v:38.5-40.8" *)
  always @(posedge clk)
    d_out_internal[7] <= xor_out[7];
  (* src = "ro_top.v:38.5-40.8" *)
  always @(posedge clk)
    d_out_internal[0] <= xor_out[0];
  (* module_not_derived = 32'd1 *)
  (* src = "ro_top.v:10.16-10.49" *)
  randModule rm0 (
    .en(en),
    .randOut(ro_out[0])
  );
  (* module_not_derived = 32'd1 *)
  (* src = "ro_top.v:11.16-11.49" *)
  randModule rm1 (
    .en(en),
    .randOut(ro_out[1])
  );
  (* module_not_derived = 32'd1 *)
  (* src = "ro_top.v:21.16-21.51" *)
  randModule rm10 (
    .en(en),
    .randOut(ro_out[10])
  );
  (* module_not_derived = 32'd1 *)
  (* src = "ro_top.v:22.16-22.51" *)
  randModule rm11 (
    .en(en),
    .randOut(ro_out[11])
  );
  (* module_not_derived = 32'd1 *)
  (* src = "ro_top.v:23.16-23.51" *)
  randModule rm12 (
    .en(en),
    .randOut(ro_out[12])
  );
  (* module_not_derived = 32'd1 *)
  (* src = "ro_top.v:24.16-24.51" *)
  randModule rm13 (
    .en(en),
    .randOut(ro_out[13])
  );
  (* module_not_derived = 32'd1 *)
  (* src = "ro_top.v:25.16-25.51" *)
  randModule rm14 (
    .en(en),
    .randOut(ro_out[14])
  );
  (* module_not_derived = 32'd1 *)
  (* src = "ro_top.v:26.16-26.51" *)
  randModule rm15 (
    .en(en),
    .randOut(ro_out[15])
  );
  (* module_not_derived = 32'd1 *)
  (* src = "ro_top.v:12.16-12.49" *)
  randModule rm2 (
    .en(en),
    .randOut(ro_out[2])
  );
  (* module_not_derived = 32'd1 *)
  (* src = "ro_top.v:13.16-13.49" *)
  randModule rm3 (
    .en(en),
    .randOut(ro_out[3])
  );
  (* module_not_derived = 32'd1 *)
  (* src = "ro_top.v:14.16-14.49" *)
  randModule rm4 (
    .en(en),
    .randOut(ro_out[4])
  );
  (* module_not_derived = 32'd1 *)
  (* src = "ro_top.v:15.16-15.49" *)
  randModule rm5 (
    .en(en),
    .randOut(ro_out[5])
  );
  (* module_not_derived = 32'd1 *)
  (* src = "ro_top.v:16.16-16.49" *)
  randModule rm6 (
    .en(en),
    .randOut(ro_out[6])
  );
  (* module_not_derived = 32'd1 *)
  (* src = "ro_top.v:17.16-17.49" *)
  randModule rm7 (
    .en(en),
    .randOut(ro_out[7])
  );
  (* module_not_derived = 32'd1 *)
  (* src = "ro_top.v:19.16-19.49" *)
  randModule rm8 (
    .en(en),
    .randOut(ro_out[8])
  );
  (* module_not_derived = 32'd1 *)
  (* src = "ro_top.v:20.16-20.49" *)
  randModule rm9 (
    .en(en),
    .randOut(ro_out[9])
  );
  assign d_out = d_out_internal;
endmodule

ro_top_tb.v
module ro_top_tb();

    reg en_tb;
    reg clk_tb;
    wire [7:0] d_out_tb;

    ro_top ro_top_I (
    .clk(clk_tb),
    .en(en_tb),
    .d_out(d_out_tb)
);

    initial begin
        clk_tb = 1'b0;
        forever #10 clk_tb=~clk_tb;
    end

    initial begin
        $dumpfile("out/ro_top.vcd");
        $dumpvars(0, ro_top_tb);

        en_tb = 1'b0;
        #30;
        en_tb = 1'b1;

        #50;

        $finish();


    end

endmodule

ro/out/ro_top.vcd
$date
	Thu Aug  8 19:48:26 2024
$end
$version
	Icarus Verilog
$end
$timescale
	1s
$end
$scope module ro_top_tb $end
$var wire 8 ! d_out_tb [7:0] $end
$var reg 1 " clk_tb $end
$var reg 1 # en_tb $end
$scope module ro_top_I $end
$var wire 1 " clk $end
$var wire 8 $ d_out [7:0] $end
$var wire 1 # en $end
$var wire 8 % xor_out [7:0] $end
$var wire 16 & ro_out [15:0] $end
$var reg 8 ' d_out_internal [7:0] $end
$scope module rm0 $end
$var wire 1 # en $end
$var wire 1 ( randOut $end
$var wire 1 ) w0 $end
$var wire 1 * w2 $end
$var wire 1 + w1 $end
$scope module notGate_1 $end
$var wire 1 ) a $end
$var wire 1 + inversedA $end
$upscope $end
$scope module notGate_2 $end
$var wire 1 + a $end
$var wire 1 * inversedA $end
$upscope $end
$upscope $end
$scope module rm1 $end
$var wire 1 # en $end
$var wire 1 , randOut $end
$var wire 1 - w0 $end
$var wire 1 . w2 $end
$var wire 1 / w1 $end
$scope module notGate_1 $end
$var wire 1 - a $end
$var wire 1 / inversedA $end
$upscope $end
$scope module notGate_2 $end
$var wire 1 / a $end
$var wire 1 . inversedA $end
$upscope $end
$upscope $end
$scope module rm10 $end
$var wire 1 # en $end
$var wire 1 0 randOut $end
$var wire 1 1 w0 $end
$var wire 1 2 w2 $end
$var wire 1 3 w1 $end
$scope module notGate_1 $end
$var wire 1 1 a $end
$var wire 1 3 inversedA $end
$upscope $end
$scope module notGate_2 $end
$var wire 1 3 a $end
$var wire 1 2 inversedA $end
$upscope $end
$upscope $end
$scope module rm11 $end
$var wire 1 # en $end
$var wire 1 4 randOut $end
$var wire 1 5 w0 $end
$var wire 1 6 w2 $end
$var wire 1 7 w1 $end
$scope module notGate_1 $end
$var wire 1 5 a $end
$var wire 1 7 inversedA $end
$upscope $end
$scope module notGate_2 $end
$var wire 1 7 a $end
$var wire 1 6 inversedA $end
$upscope $end
$upscope $end
$scope module rm12 $end
$var wire 1 # en $end
$var wire 1 8 randOut $end
$var wire 1 9 w0 $end
$var wire 1 : w2 $end
$var wire 1 ; w1 $end
$scope module notGate_1 $end
$var wire 1 9 a $end
$var wire 1 ; inversedA $end
$upscope $end
$scope module notGate_2 $end
$var wire 1 ; a $end
$var wire 1 : inversedA $end
$upscope $end
$upscope $end
$scope module rm13 $end
$var wire 1 # en $end
$var wire 1 < randOut $end
$var wire 1 = w0 $end
$var wire 1 > w2 $end
$var wire 1 ? w1 $end
$scope module notGate_1 $end
$var wire 1 = a $end
$var wire 1 ? inversedA $end
$upscope $end
$scope module notGate_2 $end
$var wire 1 ? a $end
$var wire 1 > inversedA $end
$upscope $end
$upscope $end
$scope module rm14 $end
$var wire 1 # en $end
$var wire 1 @ randOut $end
$var wire 1 A w0 $end
$var wire 1 B w2 $end
$var wire 1 C w1 $end
$scope module notGate_1 $end
$var wire 1 A a $end
$var wire 1 C inversedA $end
$upscope $end
$scope module notGate_2 $end
$var wire 1 C a $end
$var wire 1 B inversedA $end
$upscope $end
$upscope $end
$scope module rm15 $end
$var wire 1 # en $end
$var wire 1 D randOut $end
$var wire 1 E w0 $end
$var wire 1 F w2 $end
$var wire 1 G w1 $end
$scope module notGate_1 $end
$var wire 1 E a $end
$var wire 1 G inversedA $end
$upscope $end
$scope module notGate_2 $end
$var wire 1 G a $end
$var wire 1 F inversedA $end
$upscope $end
$upscope $end
$scope module rm2 $end
$var wire 1 # en $end
$var wire 1 H randOut $end
$var wire 1 I w0 $end
$var wire 1 J w2 $end
$var wire 1 K w1 $end
$scope module notGate_1 $end
$var wire 1 I a $end
$var wire 1 K inversedA $end
$upscope $end
$scope module notGate_2 $end
$var wire 1 K a $end
$var wire 1 J inversedA $end
$upscope $end
$upscope $end
$scope module rm3 $end
$var wire 1 # en $end
$var wire 1 L randOut $end
$var wire 1 M w0 $end
$var wire 1 N w2 $end
$var wire 1 O w1 $end
$scope module notGate_1 $end
$var wire 1 M a $end
$var wire 1 O inversedA $end
$upscope $end
$scope module notGate_2 $end
$var wire 1 O a $end
$var wire 1 N inversedA $end
$upscope $end
$upscope $end
$scope module rm4 $end
$var wire 1 # en $end
$var wire 1 P randOut $end
$var wire 1 Q w0 $end
$var wire 1 R w2 $end
$var wire 1 S w1 $end
$scope module notGate_1 $end
$var wire 1 Q a $end
$var wire 1 S inversedA $end
$upscope $end
$scope module notGate_2 $end
$var wire 1 S a $end
$var wire 1 R inversedA $end
$upscope $end
$upscope $end
$scope module rm5 $end
$var wire 1 # en $end
$var wire 1 T randOut $end
$var wire 1 U w0 $end
$var wire 1 V w2 $end
$var wire 1 W w1 $end
$scope module notGate_1 $end
$var wire 1 U a $end
$var wire 1 W inversedA $end
$upscope $end
$scope module notGate_2 $end
$var wire 1 W a $end
$var wire 1 V inversedA $end
$upscope $end
$upscope $end
$scope module rm6 $end
$var wire 1 # en $end
$var wire 1 X randOut $end
$var wire 1 Y w0 $end
$var wire 1 Z w2 $end
$var wire 1 [ w1 $end
$scope module notGate_1 $end
$var wire 1 Y a $end
$var wire 1 [ inversedA $end
$upscope $end
$scope module notGate_2 $end
$var wire 1 [ a $end
$var wire 1 Z inversedA $end
$upscope $end
$upscope $end
$scope module rm7 $end
$var wire 1 # en $end
$var wire 1 \ randOut $end
$var wire 1 ] w0 $end
$var wire 1 ^ w2 $end
$var wire 1 _ w1 $end
$scope module notGate_1 $end
$var wire 1 ] a $end
$var wire 1 _ inversedA $end
$upscope $end
$scope module notGate_2 $end
$var wire 1 _ a $end
$var wire 1 ^ inversedA $end
$upscope $end
$upscope $end
$scope module rm8 $end
$var wire 1 # en $end
$var wire 1 ` randOut $end
$var wire 1 a w0 $end
$var wire 1 b w2 $end
$var wire 1 c w1 $end
$scope module notGate_1 $end
$var wire 1 a a $end
$var wire 1 c inversedA $end
$upscope $end
$scope module notGate_2 $end
$var wire 1 c a $end
$var wire 1 b inversedA $end
$upscope $end
$upscope $end
$scope module rm9 $end
$var wire 1 # en $end
$var wire 1 d randOut $end
$var wire 1 e w0 $end
$var wire 1 f w2 $end
$var wire 1 g w1 $end
$scope module notGate_1 $end
$var wire 1 e a $end
$var wire 1 g inversedA $end
$upscope $end
$scope module notGate_2 $end
$var wire 1 g a $end
$var wire 1 f inversedA $end
$upscope $end
$upscope $end
$upscope $end
$upscope $end
$enddefinitions $end
$comment Show the parameter values. $end
$dumpall
$end
#0
$dumpvars
xg
xf
xe
xd
xc
xb
xa
x`
x_
x^
x]
x\
x[
xZ
xY
xX
xW
xV
xU
xT
xS
xR
xQ
xP
xO
xN
xM
xL
xK
xJ
xI
xH
xG
xF
xE
xD
xC
xB
xA
x@
x?
x>
x=
x<
x;
x:
x9
x8
x7
x6
x5
x4
x3
x2
x1
x0
x/
x.
x-
x,
x+
x*
x)
x(
bx '
bx &
bx %
bx $
0#
0"
bx !
$end
#1
1e
1a
1]
1Y
1U
1Q
1M
1I
1E
1A
1=
19
15
11
1-
1)
#2
0g
0c
0_
0[
0W
0S
0O
0K
0G
0C
0?
0;
07
03
0/
0+
#3
b0 %
b1111111111111111 &
1d
1f
1`
1b
1\
1^
1X
1Z
1T
1V
1P
1R
1L
1N
1H
1J
1D
1F
1@
1B
1<
1>
18
1:
14
16
10
12
1,
1.
1(
1*
#10
b0 !
b0 $
b0 '
1"
#20
0"
#30
1"
1#
#31
0)
0-
01
05
09
0=
0A
0E
0I
0M
0Q
0U
0Y
0]
0a
0e
#32
1+
1/
13
17
1;
1?
1C
1G
1K
1O
1S
1W
1[
1_
1c
1g
#33
b0 &
0(
0*
0,
0.
00
02
04
06
08
0:
0<
0>
0@
0B
0D
0F
0H
0J
0L
0N
0P
0R
0T
0V
0X
0Z
0\
0^
0`
0b
0d
0f
#34
1)
1-
11
15
19
1=
1A
1E
1I
1M
1Q
1U
1Y
1]
1a
1e
#35
0+
0/
03
07
0;
0?
0C
0G
0K
0O
0S
0W
0[
0_
0c
0g
#36
b1111111111111111 &
1(
1*
1,
1.
10
12
14
16
18
1:
1<
1>
1@
1B
1D
1F
1H
1J
1L
1N
1P
1R
1T
1V
1X
1Z
1\
1^
1`
1b
1d
1f
#37
0)
0-
01
05
09
0=
0A
0E
0I
0M
0Q
0U
0Y
0]
0a
0e
#38
1+
1/
13
17
1;
1?
1C
1G
1K
1O
1S
1W
1[
1_
1c
1g
#39
b0 &
0(
0*
0,
0.
00
02
04
06
08
0:
0<
0>
0@
0B
0D
0F
0H
0J
0L
0N
0P
0R
0T
0V
0X
0Z
0\
0^
0`
0b
0d
0f
#40
1)
1-
11
15
19
1=
1A
1E
1I
1M
1Q
1U
1Y
1]
1a
1e
0"
#41
0+
0/
03
07
0;
0?
0C
0G
0K
0O
0S
0W
0[
0_
0c
0g
#42
b1111111111111111 &
1(
1*
1,
1.
10
12
14
16
18
1:
1<
1>
1@
1B
1D
1F
1H
1J
1L
1N
1P
1R
1T
1V
1X
1Z
1\
1^
1`
1b
1d
1f
#43
0)
0-
01
05
09
0=
0A
0E
0I
0M
0Q
0U
0Y
0]
0a
0e
#44
1+
1/
13
17
1;
1?
1C
1G
1K
1O
1S
1W
1[
1_
1c
1g
#45
b0 &
0(
0*
0,
0.
00
02
04
06
08
0:
0<
0>
0@
0B
0D
0F
0H
0J
0L
0N
0P
0R
0T
0V
0X
0Z
0\
0^
0`
0b
0d
0f
#46
1)
1-
11
15
19
1=
1A
1E
1I
1M
1Q
1U
1Y
1]
1a
1e
#47
0+
0/
03
07
0;
0?
0C
0G
0K
0O
0S
0W
0[
0_
0c
0g
#48
b1111111111111111 &
1(
1*
1,
1.
10
12
14
16
18
1:
1<
1>
1@
1B
1D
1F
1H
1J
1L
1N
1P
1R
1T
1V
1X
1Z
1\
1^
1`
1b
1d
1f
#49
0)
0-
01
05
09
0=
0A
0E
0I
0M
0Q
0U
0Y
0]
0a
0e
#50
1+
1/
13
17
1;
1?
1C
1G
1K
1O
1S
1W
1[
1_
1c
1g
1"
#51
b0 &
0(
0*
0,
0.
00
02
04
06
08
0:
0<
0>
0@
0B
0D
0F
0H
0J
0L
0N
0P
0R
0T
0V
0X
0Z
0\
0^
0`
0b
0d
0f
#52
1)
1-
11
15
19
1=
1A
1E
1I
1M
1Q
1U
1Y
1]
1a
1e
#53
0+
0/
03
07
0;
0?
0C
0G
0K
0O
0S
0W
0[
0_
0c
0g
#54
b1111111111111111 &
1(
1*
1,
1.
10
12
14
16
18
1:
1<
1>
1@
1B
1D
1F
1H
1J
1L
1N
1P
1R
1T
1V
1X
1Z
1\
1^
1`
1b
1d
1f
#55
0)
0-
01
05
09
0=
0A
0E
0I
0M
0Q
0U
0Y
0]
0a
0e
#56
1+
1/
13
17
1;
1?
1C
1G
1K
1O
1S
1W
1[
1_
1c
1g
#57
b0 &
0(
0*
0,
0.
00
02
04
06
08
0:
0<
0>
0@
0B
0D
0F
0H
0J
0L
0N
0P
0R
0T
0V
0X
0Z
0\
0^
0`
0b
0d
0f
#58
1)
1-
11
15
19
1=
1A
1E
1I
1M
1Q
1U
1Y
1]
1a
1e
#59
0+
0/
03
07
0;
0?
0C
0G
0K
0O
0S
0W
0[
0_
0c
0g
#60
b1111111111111111 &
1(
1*
1,
1.
10
12
14
16
18
1:
1<
1>
1@
1B
1D
1F
1H
1J
1L
1N
1P
1R
1T
1V
1X
1Z
1\
1^
1`
1b
1d
1f
0"
#61
0)
0-
01
05
09
0=
0A
0E
0I
0M
0Q
0U
0Y
0]
0a
0e
#62
1+
1/
13
17
1;
1?
1C
1G
1K
1O
1S
1W
1[
1_
1c
1g
#63
b0 &
0(
0*
0,
0.
00
02
04
06
08
0:
0<
0>
0@
0B
0D
0F
0H
0J
0L
0N
0P
0R
0T
0V
0X
0Z
0\
0^
0`
0b
0d
0f
#64
1)
1-
11
15
19
1=
1A
1E
1I
1M
1Q
1U
1Y
1]
1a
1e
#65
0+
0/
03
07
0;
0?
0C
0G
0K
0O
0S
0W
0[
0_
0c
0g
#66
b1111111111111111 &
1(
1*
1,
1.
10
12
14
16
18
1:
1<
1>
1@
1B
1D
1F
1H
1J
1L
1N
1P
1R
1T
1V
1X
1Z
1\
1^
1`
1b
1d
1f
#67
0)
0-
01
05
09
0=
0A
0E
0I
0M
0Q
0U
0Y
0]
0a
0e
#68
1+
1/
13
17
1;
1?
1C
1G
1K
1O
1S
1W
1[
1_
1c
1g
#69
b0 &
0(
0*
0,
0.
00
02
04
06
08
0:
0<
0>
0@
0B
0D
0F
0H
0J
0L
0N
0P
0R
0T
0V
0X
0Z
0\
0^
0`
0b
0d
0f
#70
1)
1-
11
15
19
1=
1A
1E
1I
1M
1Q
1U
1Y
1]
1a
1e
1"
#71
0+
0/
03
07
0;
0?
0C
0G
0K
0O
0S
0W
0[
0_
0c
0g
#72
b1111111111111111 &
1(
1*
1,
1.
10
12
14
16
18
1:
1<
1>
1@
1B
1D
1F
1H
1J
1L
1N
1P
1R
1T
1V
1X
1Z
1\
1^
1`
1b
1d
1f
#73
0)
0-
01
05
09
0=
0A
0E
0I
0M
0Q
0U
0Y
0]
0a
0e
#74
1+
1/
13
17
1;
1?
1C
1G
1K
1O
1S
1W
1[
1_
1c
1g
#75
b0 &
0(
0*
0,
0.
00
02
04
06
08
0:
0<
0>
0@
0B
0D
0F
0H
0J
0L
0N
0P
0R
0T
0V
0X
0Z
0\
0^
0`
0b
0d
0f
#76
1)
1-
11
15
19
1=
1A
1E
1I
1M
1Q
1U
1Y
1]
1a
1e
#77
0+
0/
03
07
0;
0?
0C
0G
0K
0O
0S
0W
0[
0_
0c
0g
#78
b1111111111111111 &
1(
1*
1,
1.
10
12
14
16
18
1:
1<
1>
1@
1B
1D
1F
1H
1J
1L
1N
1P
1R
1T
1V
1X
1Z
1\
1^
1`
1b
1d
1f
#79
0)
0-
01
05
09
0=
0A
0E
0I
0M
0Q
0U
0Y
0]
0a
0e
#80
1+
1/
13
17
1;
1?
1C
1G
1K
1O
1S
1W
1[
1_
1c
1g
0"
